storystructure/__init__.py
storystructure/storystructure.py
storystructure-1.0.0.dist-info/LICENSE
storystructure-1.0.0.dist-info/METADATA
storystructure-1.0.0.dist-info/WHEEL
storystructure-1.0.0.dist-info/top_level.txt
storystructure-1.0.0.dist-info/RECORD
