Metadata-Version: 2.1
Name: storystructure
Version: 1.0.0
Summary: Tools for analysing the structure of branching stories
Home-page: https://github.com/sellisd/storystructure
Author: Diamantis Sellis
Author-email: sellisd@gmail.com
License: UNKNOWN
Platform: UNKNOWN
Classifier: Environment :: Console
Classifier: Intended Audience :: Science/Research
Classifier: Topic :: Scientific/Engineering
Classifier: Programming Language :: Python :: 3
